pytest_repo_structure/__init__.py
pytest_repo_structure/__main__.py
pytest_repo_structure/py.typed
pytest_repo_structure-0.0.0.dist-info/entry_points.txt
pytest_repo_structure-0.0.0.dist-info/LICENSE
pytest_repo_structure-0.0.0.dist-info/METADATA
pytest_repo_structure-0.0.0.dist-info/WHEEL
pytest_repo_structure-0.0.0.dist-info/RECORD
