Metadata-Version: 2.1
Name: pytest-repo-structure
Version: 0.0.0
Summary: Pytest Repo Structure
Home-page: https://github.com/56kyle/pytest-repo-structure
License: MIT
Author: Kyle Oliver
Author-email: 56kyleoliver@gmail.com
Requires-Python: >=3.9,<4.0
Classifier: Development Status :: 1 - Planning
Classifier: License :: OSI Approved :: MIT License
Classifier: Programming Language :: Python :: 3
Classifier: Programming Language :: Python :: 3.9
Classifier: Programming Language :: Python :: 3.10
Classifier: Programming Language :: Python :: 3.11
Requires-Dist: click (>=8.0.1)
Project-URL: Changelog, https://github.com/56kyle/pytest-repo-structure/releases
Project-URL: Documentation, https://pytest-repo-structure.readthedocs.io
Project-URL: Repository, https://github.com/56kyle/pytest-repo-structure
